[
  {
    "id": "0",
    "title": "All Day Event very long title",
    "allDay": "true",
    "start": "2021/03/12",
    "end": "2021/03/12"
  },
  {
    "id": "1",
    "title": "Meeting",
    "allDay": "false",
    "start": "2021/03/12",
    "end": "2021/03/12"
  },
  {
    "id": "2",
    "title": "Meeting",
    "allDay": "true",
    "start": "2021/03/19",
    "end": "2021/03/19"
  },
  {
    "id": "3",
    "title": "Meeting",
    "allDay": "false",
    "start": "2021/03/11",
    "end": "2021/03/11"
  },
  {
    "id": "4",
    "title": "Meeting",
    "allDay": "true",
    "start": "2021/03/24",
    "end": "2021/03/24"
  }
]
